<?xml version="1.0"?>


<chroma>
  <Input><chroma>
  <annotation>
  Calculate the Wilson loop
  </annotation>
  <Param>
    <InlineMeasurements>
      <elem>
        <!-- Wilson loops -->
        <Name>WILSLP</Name>
        <Frequency>1</Frequency>
        <Param>
          <version>3</version>
          <kind>2</kind>
          <j_decay>3</j_decay>
          <t_dir>3</t_dir>
        </Param>
        <NamedObject>
          <gauge_id>default_gauge_field</gauge_id>
        </NamedObject>
      </elem>
    </InlineMeasurements>
    <nrow>16 16 16 24</nrow>
  </Param>
  <Cfg>
    <cfg_type>SZINQIO</cfg_type>
    <cfg_file>../../config/hmc_quench_wilson_S16T24_beta6/hmc_wilson_S16T24_beta6_nstep75_cfg_606.lime</cfg_file>
    <!-- pure gauge config -->
  </Cfg>
</chroma>

  </Input>
  <ProgramInfo>
    <code_version>
      <chroma>3.44.0</chroma>
      <qdp>1.46.0</qdp>
      <basePrecision>64</basePrecision>
    </code_version>
    <run_date>14 Sep 23 09:52:13 EDT</run_date>
    <Setgeom>
      <latt_size>16 16 16 24</latt_size>
      <logical_size>1 1 1 1</logical_size>
      <subgrid_size>16 16 16 24</subgrid_size>
      <total_volume>98304</total_volume>
      <subgrid_volume>98304</subgrid_volume>
    </Setgeom>
  </ProgramInfo>
  <RNG>
    <Seed>
      <elem>11</elem>
      <elem>0</elem>
      <elem>0</elem>
      <elem>0</elem>
    </Seed>
  </RNG>
  <Config_info><Params>
      <MCControl>
        <Cfg>
          <cfg_type>SZINQIO</cfg_type>
          <cfg_file>../../config/hmc_quench_wilson_S16T24_beta6/hmc_wilson_S16T24_beta6_nstep75_cfg_606.lime</cfg_file>
          <parallel_io>false</parallel_io>
          <reunit>false</reunit>
        </Cfg>
        <RNG>
          <Seed>
            <elem>627</elem>
            <elem>2009</elem>
            <elem>619</elem>
            <elem>1970</elem>
          </Seed>
        </RNG>
        <StartUpdateNum>606</StartUpdateNum>
        <NWarmUpUpdates>0</NWarmUpUpdates>
        <NProductionUpdates>2000</NProductionUpdates>
        <NUpdatesThisRun>768</NUpdatesThisRun>
        <SaveInterval>3</SaveInterval>
        <SavePrefix>../../config/hmc_quench_wilson_S16T24_beta6/hmc_wilson_S16T24_beta6_nstep75</SavePrefix>
        <SaveVolfmt>SINGLEFILE</SaveVolfmt>
        <ParallelIO>false</ParallelIO>
        <ReproCheckP>false</ReproCheckP>
        <ReverseCheckP>true</ReverseCheckP>
        <ReverseCheckFrequency>1</ReverseCheckFrequency>
        <MonitorForces>true</MonitorForces>
        <InlineMeasurements>
</InlineMeasurements>
      </MCControl>
      <HMCTrj>
        <nrow>16 16 16 24</nrow>
        <Monomials>
          <elem>
            <Name>GAUGE_MONOMIAL</Name>
            <GaugeAction>
              <Name>WILSON_GAUGEACT</Name>
              <beta>6.0</beta>
              <GaugeBC>
                <Name>PERIODIC_GAUGEBC</Name>
              </GaugeBC>
            </GaugeAction>
            <NamedObject>
              <monomial_id>gauge</monomial_id>
            </NamedObject>
          </elem>
        </Monomials>
        <Hamiltonian>
          <monomial_ids>
            <elem>gauge</elem>
          </monomial_ids>
        </Hamiltonian>
        <MDIntegrator>
          <tau0>0.5</tau0>
          <Integrator>
            <Name>LCM_STS_LEAPFROG</Name>
            <n_steps>75</n_steps>
            <monomial_ids>
              <elem>gauge</elem>
            </monomial_ids>
          </Integrator>
        </MDIntegrator>
      </HMCTrj>
    </Params>

  </Config_info>
  <Observables>
    <w_plaq>0.593353918980982</w_plaq>
    <s_plaq>0.593146317718702</s_plaq>
    <t_plaq>0.593561520243262</t_plaq>
    <plane_01_plaq>0.593707548616836</plane_01_plaq>
    <plane_02_plaq>0.592816987708685</plane_02_plaq>
    <plane_12_plaq>0.592914416830585</plane_12_plaq>
    <plane_03_plaq>0.594495291180695</plane_03_plaq>
    <plane_13_plaq>0.59400894494382</plane_13_plaq>
    <plane_23_plaq>0.59218032460527</plane_23_plaq>
    <link>9.78920661665723e-06</link>
    <pollp>
      <elem>
        <re>0.00687664254601725</re>
        <im>-0.00493190096503952</im>
      </elem>
      <elem>
        <re>-0.00530999517955172</re>
        <im>-0.000233592400675517</im>
      </elem>
      <elem>
        <re>0.0017287204908009</re>
        <im>0.00195911306951348</im>
      </elem>
      <elem>
        <re>0.00635775936099237</re>
        <im>-0.00677639840686694</im>
      </elem>
    </pollp>
  </Observables>
  <InlineObservables>
    <elem>
      <WilsonLoop>
        <update_no>0</update_no>
        <decay_dir>3</decay_dir>
        <t_dir>3</t_dir>
        <Observables>
          <w_plaq>0.593353918980982</w_plaq>
          <s_plaq>0.593146317718702</s_plaq>
          <t_plaq>0.593561520243262</t_plaq>
          <plane_01_plaq>0.593707548616836</plane_01_plaq>
          <plane_02_plaq>0.592816987708685</plane_02_plaq>
          <plane_12_plaq>0.592914416830585</plane_12_plaq>
          <plane_03_plaq>0.594495291180695</plane_03_plaq>
          <plane_13_plaq>0.59400894494382</plane_13_plaq>
          <plane_23_plaq>0.59218032460527</plane_23_plaq>
          <link>9.7892066166572e-06</link>
          <pollp>
            <elem>
              <re>0.00687664254601725</re>
              <im>-0.00493190096503953</im>
            </elem>
            <elem>
              <re>-0.00530999517955173</re>
              <im>-0.000233592400675518</im>
            </elem>
            <elem>
              <re>0.0017287204908009</re>
              <im>0.00195911306951348</im>
            </elem>
            <elem>
              <re>0.00635775936099237</re>
              <im>-0.00677639840686694</im>
            </elem>
          </pollp>
        </Observables>
        <Link_observables>
          <w_plaq>0.593353918980982</w_plaq>
          <s_plaq>0.593146317718702</s_plaq>
          <t_plaq>0.593561520243262</t_plaq>
          <plane_01_plaq>0.593707548616836</plane_01_plaq>
          <plane_02_plaq>0.592816987708685</plane_02_plaq>
          <plane_12_plaq>0.592914416830585</plane_12_plaq>
          <plane_03_plaq>0.594495291180695</plane_03_plaq>
          <plane_13_plaq>0.594008944943821</plane_13_plaq>
          <plane_23_plaq>0.59218032460527</plane_23_plaq>
          <link>9.78920661665718e-06</link>
          <pollp>
            <elem>
              <re>0.00687664254601725</re>
              <im>-0.00493190096503953</im>
            </elem>
            <elem>
              <re>-0.00530999517955173</re>
              <im>-0.000233592400675518</im>
            </elem>
            <elem>
              <re>0.0017287204908009</re>
              <im>0.00195911306951348</im>
            </elem>
            <elem>
              <re>0.00635775936099237</re>
              <im>-0.00677639840686694</im>
            </elem>
          </pollp>
        </Link_observables>
        <wils_loop2>
          <lengthr>16</lengthr>
          <lengtht>12</lengtht>
          <wloop2>
            <elem>
              <r>0</r>
              <loop>0.593561520243264 0.383785229832644 0.252983251444859 0.167432769948099 0.110874425531764 0.0733483735436616 0.048726718670276 0.0321366713116613 0.0208861611248768 0.0139570030133675 0.00959416089814357 0.00665356357520431</loop>
            </elem>
            <elem>
              <r>1</r>
              <loop>0.383676151890377 0.1900992011866 0.101507573587283 0.0557418828410114 0.0300943579097466 0.0158425038354688 0.00881035915354384 0.00501247385404964 0.00294641035437376 0.00200161451161616 0.00121092655179291 0.000508591635525857</loop>
            </elem>
            <elem>
              <r>2</r>
              <loop>0.252425140825922 0.101554286713149 0.0473069542172957 0.0230995727756671 0.0106551789226559 0.005292551977246 0.00303752374818021 0.00186548913335598 0.0010387084761081 0.000771130927662747 0.000263735994289087 2.29503526589706e-05</loop>
            </elem>
            <elem>
              <r>3</r>
              <loop>0.16644700040078 0.0547959716183965 0.0223489998488206 0.00951640612075307 0.00427002044259178 0.00192342216582155 0.0014687365724274 0.000580652759070766 0.000902081072363733 0.000718682817037923 0.000443550213326292 0.000802448104184199</loop>
            </elem>
            <elem>
              <r>4</r>
              <loop>0.10992975269877 0.0291458050184543 0.00992995729577287 0.00430195303400444 0.00141805778091361 0.000658402515751022 0.000534831228240706 0.000658451451175406 0.000833629711536565 0.000849433772223798 -0.000295786738472215 -0.000350243697128675</loop>
            </elem>
            <elem>
              <r>5</r>
              <loop>0.0732484200173715 0.0162246238090058 0.00563253776824676 0.00248039129937412 0.000971902309095736 -0.000837731326157036 0.000542923055861719 0.000525285755684666 -0.00100072284217082 -0.000136057078301987 2.59105826758501e-05 3.82788343491122e-05</loop>
            </elem>
            <elem>
              <r>6</r>
              <loop>0.0484093684213879 0.008591817322497 0.00198091754215822 0.000117053534032935 0.000472502556004307 -0.000320332741896536 -0.000713143614281327 -0.00152391325565986 -0.00034567114578353 0.000889201352538852 -0.000282407668947335 0.00080862142997135</loop>
            </elem>
            <elem>
              <r>7</r>
              <loop>0.0321717131790101 0.00451641035596677 0.00146907394995439 0.000207897474940684 -0.000175696998780288 0.000410327290434022 0.000120264666582745 -0.000193289042181112 -8.14859230403181e-05 0.000819639541266952 0.00067649627204567 -0.000925917159468896</loop>
            </elem>
            <elem>
              <r>8</r>
              <loop>0.0211938359399944 0.00270083660564535 0.00159405637728947 0.000772603507846216 0.000220752486296775 0.000823529144564857 8.66275431865176e-05 0.000389055138883955 -0.000447295883109617 0.000380865615234597 -0.000413772047316086 -6.00223853548946e-05</loop>
            </elem>
            <elem>
              <r>9</r>
              <loop>0.0138516875016269 0.00215551173886439 0.000625168826443481 0.000420381227788045 -4.88990724842323e-05 0.000183691701352367 -0.000898958249230869 -3.51603057312246e-05 -0.000440769448038133 3.9428355869948e-05 -0.000625875038019055 -0.000306693196281507</loop>
            </elem>
            <elem>
              <r>10</r>
              <loop>0.0085898997880411 0.00134019190625948 0.000433676991324379 -0.000497184579697585 -0.000517640654905299 -0.000606762763764163 -7.26787064501139e-05 0.000319413919435084 0.000289470245695348 -0.000140399391893593 -0.000181772024951295 -4.80669309864359e-05</loop>
            </elem>
            <elem>
              <r>11</r>
              <loop>0.00543407306742163 0.0010701948004841 0.000867121684228163 0.000529222721160928 -0.000648230432160313 0.000211208617515004 0.000218250525273936 -4.29138326481771e-05 -0.000846291193592314 0.000117823384448593 0.000412342514743925 0.0001087926130677</loop>
            </elem>
            <elem>
              <r>12</r>
              <loop>0.00344839383026746 0.00051918297434495 0.00108739089849584 0.000355115694327356 -0.00034156361135761 0.000593417345486738 -5.93794027098356e-05 -7.17641215981952e-05 0.000124507357629364 0.000743529200652825 -0.000695790127598955 -0.000389078118120469</loop>
            </elem>
            <elem>
              <r>13</r>
              <loop>0.00181067647027254 0.000930069373895182 0.000948477103891054 -0.000265119147239257 0.000188221103298115 -0.000177793910978006 0.000219648359012794 -0.000449044850976154 -0.000394081538771821 -0.000456454002050187 1.43340446884708e-05 0.000204320357631794</loop>
            </elem>
            <elem>
              <r>14</r>
              <loop>0.00133025971549802 0.000585771100095037 0.000785971240566033 -6.08798961501705e-05 -0.000661263122685577 0.000492069104120776 0.000382915731682862 -0.000296166032304788 0.000191725618939683 -0.000152581153652393 4.57732061426103e-05 -0.00038117885952211</loop>
            </elem>
            <elem>
              <r>15</r>
              <loop>0.000603283330996497 0.000206109492004708 0.000345049926260521 0.000341480806392436 -0.000694409692963634 -0.000529667827162026 -0.00034533234960031 -0.000613700959281166 -0.000665379550591745 -0.000354419756634554 0.000168618293222904 -0.00127507663791324</loop>
            </elem>
          </wloop2>
        </wils_loop2>
      </WilsonLoop>
    </elem>
  </InlineObservables>
</chroma>