<?xml version="1.0"?>


<chroma>
  <Input><chroma>
  <annotation>
  Calculate the Wilson loop
  </annotation>
  <Param>
    <InlineMeasurements>
      <elem>
        <!-- Wilson loops -->
        <Name>WILSLP</Name>
        <Frequency>1</Frequency>
        <Param>
          <version>3</version>
          <kind>2</kind>
          <j_decay>3</j_decay>
          <t_dir>3</t_dir>
        </Param>
        <NamedObject>
          <gauge_id>default_gauge_field</gauge_id>
        </NamedObject>
      </elem>
    </InlineMeasurements>
    <nrow>16 16 16 24</nrow>
  </Param>
  <Cfg>
    <cfg_type>SZINQIO</cfg_type>
    <cfg_file>../../config/hmc_quench_wilson_S16T24_beta6/hmc_wilson_S16T24_beta6_nstep75_cfg_585.lime</cfg_file>
    <!-- pure gauge config -->
  </Cfg>
</chroma>

  </Input>
  <ProgramInfo>
    <code_version>
      <chroma>3.44.0</chroma>
      <qdp>1.46.0</qdp>
      <basePrecision>64</basePrecision>
    </code_version>
    <run_date>14 Sep 23 09:51:37 EDT</run_date>
    <Setgeom>
      <latt_size>16 16 16 24</latt_size>
      <logical_size>1 1 1 1</logical_size>
      <subgrid_size>16 16 16 24</subgrid_size>
      <total_volume>98304</total_volume>
      <subgrid_volume>98304</subgrid_volume>
    </Setgeom>
  </ProgramInfo>
  <RNG>
    <Seed>
      <elem>11</elem>
      <elem>0</elem>
      <elem>0</elem>
      <elem>0</elem>
    </Seed>
  </RNG>
  <Config_info><Params>
      <MCControl>
        <Cfg>
          <cfg_type>SZINQIO</cfg_type>
          <cfg_file>../../config/hmc_quench_wilson_S16T24_beta6/hmc_wilson_S16T24_beta6_nstep75_cfg_585.lime</cfg_file>
          <parallel_io>false</parallel_io>
          <reunit>false</reunit>
        </Cfg>
        <RNG>
          <Seed>
            <elem>2239</elem>
            <elem>411</elem>
            <elem>932</elem>
            <elem>1481</elem>
          </Seed>
        </RNG>
        <StartUpdateNum>585</StartUpdateNum>
        <NWarmUpUpdates>0</NWarmUpUpdates>
        <NProductionUpdates>2000</NProductionUpdates>
        <NUpdatesThisRun>768</NUpdatesThisRun>
        <SaveInterval>3</SaveInterval>
        <SavePrefix>../../config/hmc_quench_wilson_S16T24_beta6/hmc_wilson_S16T24_beta6_nstep75</SavePrefix>
        <SaveVolfmt>SINGLEFILE</SaveVolfmt>
        <ParallelIO>false</ParallelIO>
        <ReproCheckP>false</ReproCheckP>
        <ReverseCheckP>true</ReverseCheckP>
        <ReverseCheckFrequency>1</ReverseCheckFrequency>
        <MonitorForces>true</MonitorForces>
        <InlineMeasurements>
</InlineMeasurements>
      </MCControl>
      <HMCTrj>
        <nrow>16 16 16 24</nrow>
        <Monomials>
          <elem>
            <Name>GAUGE_MONOMIAL</Name>
            <GaugeAction>
              <Name>WILSON_GAUGEACT</Name>
              <beta>6.0</beta>
              <GaugeBC>
                <Name>PERIODIC_GAUGEBC</Name>
              </GaugeBC>
            </GaugeAction>
            <NamedObject>
              <monomial_id>gauge</monomial_id>
            </NamedObject>
          </elem>
        </Monomials>
        <Hamiltonian>
          <monomial_ids>
            <elem>gauge</elem>
          </monomial_ids>
        </Hamiltonian>
        <MDIntegrator>
          <tau0>0.5</tau0>
          <Integrator>
            <Name>LCM_STS_LEAPFROG</Name>
            <n_steps>75</n_steps>
            <monomial_ids>
              <elem>gauge</elem>
            </monomial_ids>
          </Integrator>
        </MDIntegrator>
      </HMCTrj>
    </Params>

  </Config_info>
  <Observables>
    <w_plaq>0.593690424174046</w_plaq>
    <s_plaq>0.594049662311373</s_plaq>
    <t_plaq>0.59333118603672</t_plaq>
    <plane_01_plaq>0.594199497673776</plane_01_plaq>
    <plane_02_plaq>0.593739022034863</plane_02_plaq>
    <plane_12_plaq>0.59421046722548</plane_12_plaq>
    <plane_03_plaq>0.59355548632146</plane_03_plaq>
    <plane_13_plaq>0.593273709609417</plane_13_plaq>
    <plane_23_plaq>0.593164362179283</plane_23_plaq>
    <link>0.000370403328419477</link>
    <pollp>
      <elem>
        <re>0.00142208291541062</re>
        <im>0.00540837082557667</im>
      </elem>
      <elem>
        <re>0.00437952453882751</re>
        <im>0.00212209359841027</im>
      </elem>
      <elem>
        <re>-0.000446110544050702</re>
        <im>0.00332245862074419</im>
      </elem>
      <elem>
        <re>-0.000641102872986816</re>
        <im>0.0029244779387369</im>
      </elem>
    </pollp>
  </Observables>
  <InlineObservables>
    <elem>
      <WilsonLoop>
        <update_no>0</update_no>
        <decay_dir>3</decay_dir>
        <t_dir>3</t_dir>
        <Observables>
          <w_plaq>0.593690424174046</w_plaq>
          <s_plaq>0.594049662311373</s_plaq>
          <t_plaq>0.59333118603672</t_plaq>
          <plane_01_plaq>0.594199497673777</plane_01_plaq>
          <plane_02_plaq>0.593739022034863</plane_02_plaq>
          <plane_12_plaq>0.59421046722548</plane_12_plaq>
          <plane_03_plaq>0.59355548632146</plane_03_plaq>
          <plane_13_plaq>0.593273709609417</plane_13_plaq>
          <plane_23_plaq>0.593164362179282</plane_23_plaq>
          <link>0.000370403328419477</link>
          <pollp>
            <elem>
              <re>0.00142208291541062</re>
              <im>0.00540837082557667</im>
            </elem>
            <elem>
              <re>0.00437952453882751</re>
              <im>0.00212209359841027</im>
            </elem>
            <elem>
              <re>-0.000446110544050702</re>
              <im>0.00332245862074419</im>
            </elem>
            <elem>
              <re>-0.000641102872986816</re>
              <im>0.0029244779387369</im>
            </elem>
          </pollp>
        </Observables>
        <Link_observables>
          <w_plaq>0.593690424174046</w_plaq>
          <s_plaq>0.594049662311373</s_plaq>
          <t_plaq>0.59333118603672</t_plaq>
          <plane_01_plaq>0.594199497673777</plane_01_plaq>
          <plane_02_plaq>0.593739022034863</plane_02_plaq>
          <plane_12_plaq>0.59421046722548</plane_12_plaq>
          <plane_03_plaq>0.59355548632146</plane_03_plaq>
          <plane_13_plaq>0.593273709609417</plane_13_plaq>
          <plane_23_plaq>0.593164362179283</plane_23_plaq>
          <link>0.000370403328419477</link>
          <pollp>
            <elem>
              <re>0.00142208291541062</re>
              <im>0.00540837082557667</im>
            </elem>
            <elem>
              <re>0.00437952453882751</re>
              <im>0.00212209359841027</im>
            </elem>
            <elem>
              <re>-0.000446110544050702</re>
              <im>0.00332245862074419</im>
            </elem>
            <elem>
              <re>-0.000641102872986816</re>
              <im>0.00292447793873689</im>
            </elem>
          </pollp>
        </Link_observables>
        <wils_loop2>
          <lengthr>16</lengthr>
          <lengtht>12</lengtht>
          <wloop2>
            <elem>
              <r>0</r>
              <loop>0.593331186036722 0.383339358504919 0.25227132885743 0.167282134539669 0.111313308311473 0.0736763508529977 0.0485924365535205 0.0322575223567318 0.0214024598615288 0.0139681898060045 0.00895828518016933 0.00549668179141426</loop>
            </elem>
            <elem>
              <r>1</r>
              <loop>0.382557292509243 0.189193734364273 0.100606363454959 0.0556976345259953 0.0303198639795506 0.0158006114325544 0.00875398613054716 0.00468966723712689 0.00248334087688981 0.00148597793194455 0.00117158191512316 0.00147716086458085</loop>
            </elem>
            <elem>
              <r>2</r>
              <loop>0.251695053037535 0.100187301409284 0.0465493249027426 0.023179149298147 0.0100263442574504 0.00549597179921855 0.00332764228191939 0.00123758110896813 0.00058615200423658 -0.000183983640985528 0.000262478764984358 0.000141747457883088</loop>
            </elem>
            <elem>
              <r>3</r>
              <loop>0.166294274140446 0.054170806528268 0.0222047885172721 0.00983176630846106 0.00431977514414758 0.00118018210379688 0.000839414720954139 0.000500183777180106 -0.000266500331453545 8.18967399589608e-05 -0.000136682963727878 -0.00012331467416882</loop>
            </elem>
            <elem>
              <r>4</r>
              <loop>0.11007563297729 0.0297100329873657 0.0112554905161038 0.00536509673848433 0.00166177722263242 0.000657558454567839 0.000191589616158454 4.91396121618637e-05 -0.00025551982202441 0.00014605669316699 0.000546120621584289 0.000548878934788636</loop>
            </elem>
            <elem>
              <r>5</r>
              <loop>0.0730198386923939 0.0175230318282708 0.00546049445265143 0.00216708092405221 0.00132217809650172 0.000375192444896873 0.000601672721597931 0.000269768375311398 -0.000541058838765382 -0.000484995336782895 -0.000803366228702399 5.8345424344958e-05</loop>
            </elem>
            <elem>
              <r>6</r>
              <loop>0.0480381018801727 0.00983149717998098 0.00327431000718253 0.000535684666166655 0.000288898485550524 0.000370038269907874 -0.000454280949938314 -0.000317706732196992 0.000213945237944522 -9.08644702125598e-05 7.35191384402672e-05 0.000584992232271604</loop>
            </elem>
            <elem>
              <r>7</r>
              <loop>0.031768397458349 0.00557245099056786 0.00154316821210681 0.000129839273756701 -0.000231412495844142 -0.000247058601672005 -0.00010878106645704 0.000381691027214341 0.000199139752281963 7.70895451602553e-05 8.46624496693076e-05 0.000262195346493906</loop>
            </elem>
            <elem>
              <r>8</r>
              <loop>0.0209699882766403 0.00382870646780354 0.00134452042491485 -0.000551387730828694 -0.000248979559506213 0.000492502694281756 -0.000261482943507174 -0.00019973033622276 -0.000538099187415036 0.000193568325105013 -0.000748175616764764 -1.22313445083388e-05</loop>
            </elem>
            <elem>
              <r>9</r>
              <loop>0.0138429466585629 0.00214888503503614 0.00103304721155964 -8.47123390291297e-05 -0.000234470173671734 0.000997298138634421 -0.000198059773472144 -0.000446735265227684 0.000142394823228708 -0.000776358233430536 0.000749992209327299 6.6059816841669e-05</loop>
            </elem>
            <elem>
              <r>10</r>
              <loop>0.00911942888252923 0.00139542016647752 0.000697954237040252 -0.000288659067415197 0.000204295639772088 0.000672435237047426 0.000180529863372697 0.000106464165434227 0.000418987374136242 0.000214078712716269 0.000470309045160033 0.000112426707880618</loop>
            </elem>
            <elem>
              <r>11</r>
              <loop>0.00583900178950721 0.000384686966974782 0.000989650122442288 -0.000603884875415727 -9.91028675587331e-05 -0.000150813671741148 -0.000268513579265799 0.000138675297983016 0.000318912598229131 -0.000342646454612815 -0.0006474359610691 -0.00044926839476146</loop>
            </elem>
            <elem>
              <r>12</r>
              <loop>0.00340615627074861 0.000511963275917556 0.000252020938118954 -0.000192903838745232 5.12094473313415e-05 0.000420665889866243 -0.000548449968842865 0.000306079272583809 0.000351247183227711 0.000187129769555228 -4.16505506133744e-05 -0.000421175456408294</loop>
            </elem>
            <elem>
              <r>13</r>
              <loop>0.00188327875903731 0.000396726502921549 -0.000379794564723804 -0.00050902066539542 0.000448024901480747 4.76537048513926e-05 0.00101989199574475 0.000231945658807951 0.000774867377889564 0.000314076105255736 -4.80297043258267e-05 -0.000134374939245967</loop>
            </elem>
            <elem>
              <r>14</r>
              <loop>0.00121786767187322 0.00181512529193973 -0.000901622773372543 0.000559748048692387 0.000172361357068665 2.64758506591058e-06 -0.000935982232490591 0.000572674481855227 -0.000461353268751497 -0.0004681586460894 0.00049571277077132 0.000256390199229447</loop>
            </elem>
            <elem>
              <r>15</r>
              <loop>0.000936857055046696 0.00136150137920926 -0.000471975863060574 -0.000502727743767907 0.00025353798740697 0.000470376431635748 -0.0003569525596547 0.000460126976863615 0.00120255926153242 -0.00107121943654109 0.0015652851865972 -0.000633437218212751</loop>
            </elem>
          </wloop2>
        </wils_loop2>
      </WilsonLoop>
    </elem>
  </InlineObservables>
</chroma>